aston/__init__.py
aston/constants.py
aston/version.py
aston/analysis/__init__.py
aston/analysis/critical_path.py
aston/analysis/criticality_go.py
aston/analysis/criticality_scorer.py
aston/analysis/diff_analyzer.py
aston/analysis/regression_guard.py
aston/analysis/coverage/__init__.py
aston/analysis/coverage/gap_detector.py
aston/analysis/coverage/ingest.py
aston/analysis/coverage/mapping.py
aston/analysis/coverage/models.py
aston/analysis/coverage/reports.py
aston/analysis/coverage/utils.py
aston/analysis/suggest/__init__.py
aston/analysis/suggest/data_loaders.py
aston/analysis/suggest/engine.py
aston/analysis/suggest/exceptions.py
aston/analysis/suggest/generators/__init__.py
aston/analysis/suggest/generators/heuristic.py
aston/analysis/suggest/generators/llm.py
aston/analysis/test_quality/__init__.py
aston/analysis/test_quality/analyzer.py
aston/analysis/test_quality/metrics.py
aston/analysis/test_quality/report_generator.py
aston/analysis/utils/__init__.py
aston/api/__init__.py
aston/api/coverage_map.py
aston/api/github_bot.py
aston/bin/aston-rank-darwin-amd64
aston/bin/aston-rank-darwin-arm64
aston/bin/aston-rank-linux-amd64
aston/bin/aston-rank-windows-amd64.exe
aston/cli/__init__.py
aston/cli/common_filters.py
aston/cli/main.py
aston/cli/commands/__init__.py
aston/cli/commands/cache.py
aston/cli/commands/check.py
aston/cli/commands/cov.py
aston/cli/commands/coverage.py
aston/cli/commands/criticality.py
aston/cli/commands/diff.py
aston/cli/commands/embed.py
aston/cli/commands/graph.py
aston/cli/commands/ingest_coverage.py
aston/cli/commands/init.py
aston/cli/commands/refresh.py
aston/cli/commands/regression_guard.py
aston/cli/commands/run_pytest_with_coverage.py
aston/cli/commands/suggest.py
aston/cli/commands/test.py
aston/cli/commands/test_suggest.py
aston/cli/utils/__init__.py
aston/cli/utils/env_check.py
aston/core/__init__.py
aston/core/config.py
aston/core/exceptions.py
aston/core/filter_contract.py
aston/core/filtering.py
aston/core/logging.py
astonai-0.3.8.dist-info/METADATA
astonai-0.3.8.dist-info/WHEEL
astonai-0.3.8.dist-info/entry_points.txt
astonai-0.3.8.dist-info/top_level.txt
astonai-0.3.8.dist-info/RECORD
