Metadata-Version: 2.4
Name: astonai
Version: 0.3.8
Summary: Test Intelligence Engine
Author: Aston AI
License: MIT
Keywords: aston,test coverage,static analysis
Requires-Python: >=3.8
Requires-Dist: numpy<2.3,>=1.22.0
Requires-Dist: pydantic<3.0,>=1.10.0
Requires-Dist: click<9.0,>=8.1.3
Requires-Dist: rich<15.0,>=12.5.1
Requires-Dist: PyYAML<7.0,>=6.0
Requires-Dist: gitpython<4.0,>=3.1.0
Requires-Dist: astgraph<0.2.0,>=0.1.0
Requires-Dist: networkx<4.0,>=3.0.0
Requires-Dist: parso<1.0,>=0.8.0
Requires-Dist: libcst<2.0,>=1.0.0
Provides-Extra: db
Requires-Dist: neo4j<6.0,>=5.5.0; extra == "db"
Provides-Extra: viz
Requires-Dist: matplotlib<3.12,>=3.8; extra == "viz"
Provides-Extra: llm
Requires-Dist: openai<2.0,>=1.0.0; extra == "llm"
Provides-Extra: embed
Requires-Dist: sentence-transformers<3.0,>=2.0.0; extra == "embed"
Requires-Dist: faiss-cpu>=1.7.0; extra == "embed"
Requires-Dist: aiohttp<4.0,>=3.8.0; extra == "embed"
Provides-Extra: test
Requires-Dist: pytest<9.0,>=8.0.0; extra == "test"
Requires-Dist: pytest-cov<5.0,>=4.1.0; extra == "test"
Requires-Dist: pytest-xdist<4.0,>=3.0.0; extra == "test"
Requires-Dist: pytest-asyncio<1.0,>=0.21.0; extra == "test"
Requires-Dist: mypy<2.0,>=1.0.0; extra == "test"
Requires-Dist: flake8<8.0,>=6.0.0; extra == "test"
Requires-Dist: packaging<25.0,>=23.0; extra == "test"
Requires-Dist: aioresponses<1.0,>=0.7.0; extra == "test"
Provides-Extra: coverage
Requires-Dist: pytest-cov<5.0,>=4.1.0; extra == "coverage"
Requires-Dist: coverage-conditional-plugin<1.0,>=0.9.0; extra == "coverage"
Provides-Extra: dev
Requires-Dist: astonai[coverage,db,embed,llm,test,viz]; extra == "dev"
Requires-Dist: build<2.0,>=1.0.0; extra == "dev"
Requires-Dist: twine<6.0,>=4.0.0; extra == "dev"
Provides-Extra: all
Requires-Dist: astonai[coverage,db,embed,llm,test,viz]; extra == "all"
